[
  {
    "id": 1,
    "address1": "4821 NW Everett St",
    "city": "Portland",
    "state": "OR",
    "zip": "97210",
    "used": true,
    "addedAt": "2026-04-11T23:33:19.482Z"
  },
  {
    "id": 2,
    "address1": "1537 SE Hawthorne Blvd",
    "city": "Portland",
    "state": "OR",
    "zip": "97214",
    "used": true,
    "addedAt": "2026-04-11T23:33:19.483Z"
  },
  {
    "id": 3,
    "address1": "2903 NE Broadway St",
    "city": "Portland",
    "state": "OR",
    "zip": "97232",
    "used": true,
    "addedAt": "2026-04-11T23:33:19.483Z"
  },
  {
    "id": 4,
    "address1": "7614 SW Barbur Blvd",
    "city": "Portland",
    "state": "OR",
    "zip": "97219",
    "used": true,
    "addedAt": "2026-04-11T23:33:19.483Z"
  },
  {
    "id": 5,
    "address1": "3342 SE Division St",
    "city": "Portland",
    "state": "OR",
    "zip": "97202",
    "used": true,
    "addedAt": "2026-04-11T23:33:19.483Z"
  },
  {
    "id": 6,
    "address1": "1028 NW 23rd Ave",
    "city": "Portland",
    "state": "OR",
    "zip": "97210",
    "used": true,
    "addedAt": "2026-04-11T23:33:19.483Z"
  },
  {
    "id": 7,
    "address1": "5519 N Interstate Ave",
    "city": "Portland",
    "state": "OR",
    "zip": "97217",
    "used": true,
    "addedAt": "2026-04-11T23:33:19.483Z"
  },
  {
    "id": 8,
    "address1": "8745 SE Foster Rd",
    "city": "Portland",
    "state": "OR",
    "zip": "97266",
    "used": true,
    "addedAt": "2026-04-11T23:33:19.483Z"
  },
  {
    "id": 9,
    "address1": "2210 NE Alberta St",
    "city": "Portland",
    "state": "OR",
    "zip": "97211",
    "used": true,
    "addedAt": "2026-04-11T23:33:19.483Z"
  },
  {
    "id": 10,
    "address1": "6437 SW Capitol Hwy",
    "city": "Portland",
    "state": "OR",
    "zip": "97239",
    "used": true,
    "addedAt": "2026-04-11T23:33:19.483Z"
  },
  {
    "id": 11,
    "address1": "1845 Willamette St",
    "city": "Eugene",
    "state": "OR",
    "zip": "97401",
    "used": true,
    "addedAt": "2026-04-11T23:33:19.483Z"
  },
  {
    "id": 12,
    "address1": "3021 River Rd",
    "city": "Eugene",
    "state": "OR",
    "zip": "97404",
    "used": true,
    "addedAt": "2026-04-11T23:33:19.483Z"
  },
  {
    "id": 13,
    "address1": "578 E 13th Ave",
    "city": "Eugene",
    "state": "OR",
    "zip": "97401",
    "used": true,
    "addedAt": "2026-04-11T23:33:19.483Z"
  },
  {
    "id": 14,
    "address1": "2490 Hilyard St",
    "city": "Eugene",
    "state": "OR",
    "zip": "97405",
    "used": true,
    "addedAt": "2026-04-11T23:33:19.483Z"
  },
  {
    "id": 15,
    "address1": "4013 W 11th Ave",
    "city": "Eugene",
    "state": "OR",
    "zip": "97402",
    "used": true,
    "addedAt": "2026-04-11T23:33:19.483Z"
  },
  {
    "id": 16,
    "address1": "1122 Oak St",
    "city": "Eugene",
    "state": "OR",
    "zip": "97401",
    "used": true,
    "addedAt": "2026-04-11T23:33:19.483Z"
  },
  {
    "id": 17,
    "address1": "3685 Donald St",
    "city": "Eugene",
    "state": "OR",
    "zip": "97405",
    "used": true,
    "addedAt": "2026-04-11T23:33:19.483Z"
  },
  {
    "id": 18,
    "address1": "890 Bailey Hill Rd",
    "city": "Eugene",
    "state": "OR",
    "zip": "97402",
    "used": true,
    "addedAt": "2026-04-11T23:33:19.483Z"
  },
  {
    "id": 19,
    "address1": "2754 Chambers St",
    "city": "Eugene",
    "state": "OR",
    "zip": "97405",
    "used": true,
    "addedAt": "2026-04-11T23:33:19.483Z"
  },
  {
    "id": 20,
    "address1": "1467 Alder St",
    "city": "Eugene",
    "state": "OR",
    "zip": "97401",
    "used": true,
    "addedAt": "2026-04-11T23:33:19.483Z"
  },
  {
    "id": 21,
    "address1": "3218 Commercial St SE",
    "city": "Salem",
    "state": "OR",
    "zip": "97302",
    "used": true,
    "addedAt": "2026-04-11T23:33:19.483Z"
  },
  {
    "id": 22,
    "address1": "1540 Center St NE",
    "city": "Salem",
    "state": "OR",
    "zip": "97301",
    "used": true,
    "addedAt": "2026-04-11T23:33:19.483Z"
  },
  {
    "id": 23,
    "address1": "4725 Lancaster Dr NE",
    "city": "Salem",
    "state": "OR",
    "zip": "97305",
    "used": true,
    "addedAt": "2026-04-11T23:33:19.483Z"
  },
  {
    "id": 24,
    "address1": "2087 Liberty St S",
    "city": "Salem",
    "state": "OR",
    "zip": "97302",
    "used": true,
    "addedAt": "2026-04-11T23:33:19.483Z"
  },
  {
    "id": 25,
    "address1": "985 Hawthorne Ave NE",
    "city": "Salem",
    "state": "OR",
    "zip": "97301",
    "used": true,
    "addedAt": "2026-04-11T23:33:19.483Z"
  },
  {
    "id": 26,
    "address1": "3461 Silverton Rd NE",
    "city": "Salem",
    "state": "OR",
    "zip": "97305",
    "used": true,
    "addedAt": "2026-04-11T23:33:19.483Z"
  },
  {
    "id": 27,
    "address1": "1273 State St",
    "city": "Salem",
    "state": "OR",
    "zip": "97301",
    "used": true,
    "addedAt": "2026-04-11T23:33:19.483Z"
  },
  {
    "id": 28,
    "address1": "5640 Portland Rd NE",
    "city": "Salem",
    "state": "OR",
    "zip": "97305",
    "used": true,
    "addedAt": "2026-04-11T23:33:19.483Z"
  },
  {
    "id": 29,
    "address1": "2819 12th St SE",
    "city": "Salem",
    "state": "OR",
    "zip": "97302",
    "used": true,
    "addedAt": "2026-04-11T23:33:19.483Z"
  },
  {
    "id": 30,
    "address1": "760 Mission St SE",
    "city": "Salem",
    "state": "OR",
    "zip": "97302",
    "used": true,
    "addedAt": "2026-04-11T23:33:19.483Z"
  },
  {
    "id": 31,
    "address1": "1435 NW Stewart Pkwy",
    "city": "Roseburg",
    "state": "OR",
    "zip": "97471",
    "used": true,
    "addedAt": "2026-04-11T23:33:19.483Z"
  },
  {
    "id": 32,
    "address1": "2813 NE Diamond Lake Blvd",
    "city": "Roseburg",
    "state": "OR",
    "zip": "97470",
    "used": true,
    "addedAt": "2026-04-11T23:33:19.483Z"
  },
  {
    "id": 33,
    "address1": "547 SE Jackson St",
    "city": "Roseburg",
    "state": "OR",
    "zip": "97470",
    "used": true,
    "addedAt": "2026-04-11T23:33:19.483Z"
  },
  {
    "id": 34,
    "address1": "1920 W Harvard Ave",
    "city": "Roseburg",
    "state": "OR",
    "zip": "97471",
    "used": true,
    "addedAt": "2026-04-11T23:33:19.483Z"
  },
  {
    "id": 35,
    "address1": "3102 NE Stephens St",
    "city": "Roseburg",
    "state": "OR",
    "zip": "97470",
    "used": true,
    "addedAt": "2026-04-11T23:33:19.483Z"
  },
  {
    "id": 36,
    "address1": "4521 NE Alameda Ave",
    "city": "Bend",
    "state": "OR",
    "zip": "97701",
    "used": true,
    "addedAt": "2026-04-11T23:33:19.483Z"
  },
  {
    "id": 37,
    "address1": "1837 NW Galveston Ave",
    "city": "Bend",
    "state": "OR",
    "zip": "97703",
    "used": true,
    "addedAt": "2026-04-11T23:33:19.483Z"
  },
  {
    "id": 38,
    "address1": "6214 SW Century Dr",
    "city": "Bend",
    "state": "OR",
    "zip": "97702",
    "used": true,
    "addedAt": "2026-04-11T23:33:19.483Z"
  },
  {
    "id": 39,
    "address1": "2950 NE Neff Rd",
    "city": "Bend",
    "state": "OR",
    "zip": "97701",
    "used": true,
    "addedAt": "2026-04-11T23:33:19.483Z"
  },
  {
    "id": 40,
    "address1": "1103 NW Newport Ave",
    "city": "Bend",
    "state": "OR",
    "zip": "97703",
    "used": true,
    "addedAt": "2026-04-11T23:33:19.483Z"
  },
  {
    "id": 41,
    "address1": "3478 SW Canal Blvd",
    "city": "Redmond",
    "state": "OR",
    "zip": "97756",
    "used": true,
    "addedAt": "2026-04-11T23:33:19.483Z"
  },
  {
    "id": 42,
    "address1": "820 NW Dogwood Ave",
    "city": "Redmond",
    "state": "OR",
    "zip": "97756",
    "used": true,
    "addedAt": "2026-04-11T23:33:19.483Z"
  },
  {
    "id": 43,
    "address1": "2145 SW Reindeer Ave",
    "city": "Redmond",
    "state": "OR",
    "zip": "97756",
    "used": true,
    "addedAt": "2026-04-11T23:33:19.483Z"
  },
  {
    "id": 44,
    "address1": "5532 S 6th St",
    "city": "Redmond",
    "state": "OR",
    "zip": "97756",
    "used": true,
    "addedAt": "2026-04-11T23:33:19.483Z"
  },
  {
    "id": 45,
    "address1": "1679 NW Maple Ave",
    "city": "Redmond",
    "state": "OR",
    "zip": "97756",
    "used": true,
    "addedAt": "2026-04-11T23:33:19.483Z"
  },
  {
    "id": 46,
    "address1": "2341 Table Rock Rd",
    "city": "Medford",
    "state": "OR",
    "zip": "97501",
    "used": true,
    "addedAt": "2026-04-11T23:33:19.483Z"
  },
  {
    "id": 47,
    "address1": "1578 E Main St",
    "city": "Medford",
    "state": "OR",
    "zip": "97504",
    "used": true,
    "addedAt": "2026-04-11T23:33:19.483Z"
  },
  {
    "id": 48,
    "address1": "4210 Crater Lake Ave",
    "city": "Medford",
    "state": "OR",
    "zip": "97504",
    "used": true,
    "addedAt": "2026-04-11T23:33:19.483Z"
  },
  {
    "id": 49,
    "address1": "873 N Central Ave",
    "city": "Medford",
    "state": "OR",
    "zip": "97501",
    "used": true,
    "addedAt": "2026-04-11T23:33:19.483Z"
  },
  {
    "id": 50,
    "address1": "3095 Biddle Rd",
    "city": "Medford",
    "state": "OR",
    "zip": "97504",
    "used": true,
    "addedAt": "2026-04-11T23:33:19.483Z"
  },
  {
    "id": 51,
    "address1": "1742 Delta Waters Rd",
    "city": "Medford",
    "state": "OR",
    "zip": "97504",
    "used": true,
    "addedAt": "2026-04-11T23:33:19.483Z"
  },
  {
    "id": 52,
    "address1": "2568 Barnett Rd",
    "city": "Medford",
    "state": "OR",
    "zip": "97501",
    "used": true,
    "addedAt": "2026-04-11T23:33:19.483Z"
  },
  {
    "id": 53,
    "address1": "519 W Main St",
    "city": "Medford",
    "state": "OR",
    "zip": "97501",
    "used": true,
    "addedAt": "2026-04-11T23:33:19.483Z"
  },
  {
    "id": 54,
    "address1": "4387 N Phoenix Rd",
    "city": "Medford",
    "state": "OR",
    "zip": "97504",
    "used": true,
    "addedAt": "2026-04-11T23:33:19.483Z"
  },
  {
    "id": 55,
    "address1": "1053 Court St",
    "city": "Medford",
    "state": "OR",
    "zip": "97501",
    "used": true,
    "addedAt": "2026-04-11T23:33:19.483Z"
  },
  {
    "id": 56,
    "address1": "3821 Siskiyou Blvd",
    "city": "Ashland",
    "state": "OR",
    "zip": "97520",
    "used": true,
    "addedAt": "2026-04-11T23:33:19.483Z"
  },
  {
    "id": 57,
    "address1": "1247 Oak St",
    "city": "Ashland",
    "state": "OR",
    "zip": "97520",
    "used": true,
    "addedAt": "2026-04-11T23:33:19.483Z"
  },
  {
    "id": 58,
    "address1": "2590 Ashland St",
    "city": "Ashland",
    "state": "OR",
    "zip": "97520",
    "used": true,
    "addedAt": "2026-04-11T23:33:19.483Z"
  },
  {
    "id": 59,
    "address1": "478 A St",
    "city": "Ashland",
    "state": "OR",
    "zip": "97520",
    "used": true,
    "addedAt": "2026-04-11T23:33:19.483Z"
  },
  {
    "id": 60,
    "address1": "1835 Tolman Creek Rd",
    "city": "Ashland",
    "state": "OR",
    "zip": "97520",
    "used": true,
    "addedAt": "2026-04-11T23:33:19.483Z"
  },
  {
    "id": 61,
    "address1": "2917 NW Highland Ave",
    "city": "Grants Pass",
    "state": "OR",
    "zip": "97526",
    "used": true,
    "addedAt": "2026-04-11T23:33:19.483Z"
  },
  {
    "id": 62,
    "address1": "1543 Rogue River Hwy",
    "city": "Grants Pass",
    "state": "OR",
    "zip": "97527",
    "used": true,
    "addedAt": "2026-04-11T23:33:19.483Z"
  },
  {
    "id": 63,
    "address1": "4208 Williams Hwy",
    "city": "Grants Pass",
    "state": "OR",
    "zip": "97527",
    "used": true,
    "addedAt": "2026-04-11T23:33:19.483Z"
  },
  {
    "id": 64,
    "address1": "732 SE 7th St",
    "city": "Grants Pass",
    "state": "OR",
    "zip": "97526",
    "used": true,
    "addedAt": "2026-04-11T23:33:19.483Z"
  },
  {
    "id": 65,
    "address1": "1875 NE E St",
    "city": "Grants Pass",
    "state": "OR",
    "zip": "97526",
    "used": true,
    "addedAt": "2026-04-11T23:33:19.483Z"
  },
  {
    "id": 66,
    "address1": "3124 Pacific Blvd SW",
    "city": "Albany",
    "state": "OR",
    "zip": "97321",
    "used": true,
    "addedAt": "2026-04-11T23:33:19.483Z"
  },
  {
    "id": 67,
    "address1": "1456 Geary St SE",
    "city": "Albany",
    "state": "OR",
    "zip": "97322",
    "used": true,
    "addedAt": "2026-04-11T23:33:19.483Z"
  },
  {
    "id": 68,
    "address1": "2780 Santiam Hwy SE",
    "city": "Albany",
    "state": "OR",
    "zip": "97322",
    "used": true,
    "addedAt": "2026-04-11T23:33:19.483Z"
  },
  {
    "id": 69,
    "address1": "835 Lyon St SE",
    "city": "Albany",
    "state": "OR",
    "zip": "97321",
    "used": true,
    "addedAt": "2026-04-11T23:33:19.483Z"
  },
  {
    "id": 70,
    "address1": "4091 Knox Butte Rd E",
    "city": "Albany",
    "state": "OR",
    "zip": "97322",
    "used": true,
    "addedAt": "2026-04-11T23:33:19.483Z"
  },
  {
    "id": 71,
    "address1": "1327 NW Monroe Ave",
    "city": "Corvallis",
    "state": "OR",
    "zip": "97330",
    "used": true,
    "addedAt": "2026-04-11T23:33:19.483Z"
  },
  {
    "id": 72,
    "address1": "2548 NW 9th St",
    "city": "Corvallis",
    "state": "OR",
    "zip": "97330",
    "used": true,
    "addedAt": "2026-04-11T23:33:19.483Z"
  },
  {
    "id": 73,
    "address1": "4715 SW Philomath Blvd",
    "city": "Corvallis",
    "state": "OR",
    "zip": "97333",
    "used": true,
    "addedAt": "2026-04-11T23:33:19.483Z"
  },
  {
    "id": 74,
    "address1": "893 SE 3rd St",
    "city": "Corvallis",
    "state": "OR",
    "zip": "97333",
    "used": true,
    "addedAt": "2026-04-11T23:33:19.483Z"
  },
  {
    "id": 75,
    "address1": "3201 NW Harrison Blvd",
    "city": "Corvallis",
    "state": "OR",
    "zip": "97330",
    "used": true,
    "addedAt": "2026-04-11T23:33:19.483Z"
  },
  {
    "id": 76,
    "address1": "1640 NW Circle Blvd",
    "city": "Corvallis",
    "state": "OR",
    "zip": "97330",
    "used": true,
    "addedAt": "2026-04-11T23:33:19.483Z"
  },
  {
    "id": 77,
    "address1": "2012 SW Western Blvd",
    "city": "Corvallis",
    "state": "OR",
    "zip": "97333",
    "used": true,
    "addedAt": "2026-04-11T23:33:19.483Z"
  },
  {
    "id": 78,
    "address1": "574 NW 23rd St",
    "city": "Corvallis",
    "state": "OR",
    "zip": "97330",
    "used": true,
    "addedAt": "2026-04-11T23:33:19.483Z"
  },
  {
    "id": 79,
    "address1": "3847 SE Crystal Lake Dr",
    "city": "Corvallis",
    "state": "OR",
    "zip": "97333",
    "used": true,
    "addedAt": "2026-04-11T23:33:19.483Z"
  },
  {
    "id": 80,
    "address1": "1185 NW Van Buren Ave",
    "city": "Corvallis",
    "state": "OR",
    "zip": "97330",
    "used": true,
    "addedAt": "2026-04-11T23:33:19.483Z"
  },
  {
    "id": 81,
    "address1": "4523 SW Western Ave",
    "city": "Beaverton",
    "state": "OR",
    "zip": "97005",
    "used": true,
    "addedAt": "2026-04-11T23:33:19.483Z"
  },
  {
    "id": 82,
    "address1": "1897 NW Cornell Rd",
    "city": "Beaverton",
    "state": "OR",
    "zip": "97006",
    "used": true,
    "addedAt": "2026-04-11T23:33:19.483Z"
  },
  {
    "id": 83,
    "address1": "3210 SW Cedar Hills Blvd",
    "city": "Beaverton",
    "state": "OR",
    "zip": "97005",
    "used": true,
    "addedAt": "2026-04-11T23:33:19.483Z"
  },
  {
    "id": 84,
    "address1": "760 SW Hall Blvd",
    "city": "Beaverton",
    "state": "OR",
    "zip": "97005",
    "used": true,
    "addedAt": "2026-04-11T23:33:19.483Z"
  },
  {
    "id": 85,
    "address1": "2458 NW 185th Ave",
    "city": "Beaverton",
    "state": "OR",
    "zip": "97006",
    "used": true,
    "addedAt": "2026-04-11T23:33:19.483Z"
  },
  {
    "id": 86,
    "address1": "5143 SW Lombard Ave",
    "city": "Beaverton",
    "state": "OR",
    "zip": "97005",
    "used": true,
    "addedAt": "2026-04-11T23:33:19.483Z"
  },
  {
    "id": 87,
    "address1": "1329 SW Tualatin Valley Hwy",
    "city": "Beaverton",
    "state": "OR",
    "zip": "97003",
    "used": true,
    "addedAt": "2026-04-11T23:33:19.483Z"
  },
  {
    "id": 88,
    "address1": "3874 NW Science Park Dr",
    "city": "Beaverton",
    "state": "OR",
    "zip": "97006",
    "used": true,
    "addedAt": "2026-04-11T23:33:19.483Z"
  },
  {
    "id": 89,
    "address1": "2091 SW Murray Blvd",
    "city": "Beaverton",
    "state": "OR",
    "zip": "97005",
    "used": true,
    "addedAt": "2026-04-11T23:33:19.483Z"
  },
  {
    "id": 90,
    "address1": "647 SW 158th Ave",
    "city": "Beaverton",
    "state": "OR",
    "zip": "97006",
    "used": true,
    "addedAt": "2026-04-11T23:33:19.483Z"
  },
  {
    "id": 91,
    "address1": "1542 Molalla Ave",
    "city": "Oregon City",
    "state": "OR",
    "zip": "97045",
    "used": true,
    "addedAt": "2026-04-11T23:33:19.483Z"
  },
  {
    "id": 92,
    "address1": "3218 Beavercreek Rd",
    "city": "Oregon City",
    "state": "OR",
    "zip": "97045",
    "used": true,
    "addedAt": "2026-04-11T23:33:19.483Z"
  },
  {
    "id": 93,
    "address1": "875 7th St",
    "city": "Oregon City",
    "state": "OR",
    "zip": "97045",
    "used": true,
    "addedAt": "2026-04-11T23:33:19.483Z"
  },
  {
    "id": 94,
    "address1": "2403 Linn Ave",
    "city": "Oregon City",
    "state": "OR",
    "zip": "97045",
    "used": true,
    "addedAt": "2026-04-11T23:33:19.483Z"
  },
  {
    "id": 95,
    "address1": "1780 Washington St",
    "city": "Oregon City",
    "state": "OR",
    "zip": "97045",
    "used": true,
    "addedAt": "2026-04-11T23:33:19.483Z"
  },
  {
    "id": 96,
    "address1": "4512 82nd Dr",
    "city": "Lake Oswego",
    "state": "OR",
    "zip": "97035",
    "used": true,
    "addedAt": "2026-04-11T23:33:19.483Z"
  },
  {
    "id": 97,
    "address1": "2175 Kruse Way",
    "city": "Lake Oswego",
    "state": "OR",
    "zip": "97035",
    "used": true,
    "addedAt": "2026-04-11T23:33:19.483Z"
  },
  {
    "id": 98,
    "address1": "1340 A Ave",
    "city": "Lake Oswego",
    "state": "OR",
    "zip": "97034",
    "used": true,
    "addedAt": "2026-04-11T23:33:19.483Z"
  },
  {
    "id": 99,
    "address1": "3620 Lakeview Blvd",
    "city": "Lake Oswego",
    "state": "OR",
    "zip": "97035",
    "used": true,
    "addedAt": "2026-04-11T23:33:19.483Z"
  },
  {
    "id": 100,
    "address1": "589 3rd St",
    "city": "Lake Oswego",
    "state": "OR",
    "zip": "97034",
    "used": true,
    "addedAt": "2026-04-11T23:33:19.483Z"
  },
  {
    "id": 101,
    "address1": "2741 Country Club Rd",
    "city": "Lake Oswego",
    "state": "OR",
    "zip": "97034",
    "used": true,
    "addedAt": "2026-04-11T23:33:19.483Z"
  },
  {
    "id": 102,
    "address1": "1893 Boones Ferry Rd",
    "city": "Lake Oswego",
    "state": "OR",
    "zip": "97035",
    "used": true,
    "addedAt": "2026-04-11T23:33:19.483Z"
  },
  {
    "id": 103,
    "address1": "4108 Jean Rd",
    "city": "Lake Oswego",
    "state": "OR",
    "zip": "97034",
    "used": true,
    "addedAt": "2026-04-11T23:33:19.483Z"
  },
  {
    "id": 104,
    "address1": "670 Evergreen Rd",
    "city": "Lake Oswego",
    "state": "OR",
    "zip": "97034",
    "used": true,
    "addedAt": "2026-04-11T23:33:19.483Z"
  },
  {
    "id": 105,
    "address1": "3056 Upper Dr",
    "city": "Lake Oswego",
    "state": "OR",
    "zip": "97035",
    "used": true,
    "addedAt": "2026-04-11T23:33:19.483Z"
  },
  {
    "id": 106,
    "address1": "1428 SW 1st Ave",
    "city": "Hillsboro",
    "state": "OR",
    "zip": "97123",
    "used": true,
    "addedAt": "2026-04-11T23:33:19.483Z"
  },
  {
    "id": 107,
    "address1": "3745 NE Cornell Rd",
    "city": "Hillsboro",
    "state": "OR",
    "zip": "97124",
    "used": true,
    "addedAt": "2026-04-11T23:33:19.483Z"
  },
  {
    "id": 108,
    "address1": "2580 SE Tualatin Valley Hwy",
    "city": "Hillsboro",
    "state": "OR",
    "zip": "97123",
    "used": true,
    "addedAt": "2026-04-11T23:33:19.483Z"
  },
  {
    "id": 109,
    "address1": "915 NW 229th Ave",
    "city": "Hillsboro",
    "state": "OR",
    "zip": "97124",
    "used": true,
    "addedAt": "2026-04-11T23:33:19.483Z"
  },
  {
    "id": 110,
    "address1": "4321 NE Century Blvd",
    "city": "Hillsboro",
    "state": "OR",
    "zip": "97124",
    "used": true,
    "addedAt": "2026-04-11T23:33:19.483Z"
  },
  {
    "id": 111,
    "address1": "1673 SE Baseline St",
    "city": "Hillsboro",
    "state": "OR",
    "zip": "97123",
    "used": true,
    "addedAt": "2026-04-11T23:33:19.483Z"
  },
  {
    "id": 112,
    "address1": "2847 NW Aloclek Dr",
    "city": "Hillsboro",
    "state": "OR",
    "zip": "97124",
    "used": true,
    "addedAt": "2026-04-11T23:33:19.483Z"
  },
  {
    "id": 113,
    "address1": "530 SE Oak St",
    "city": "Hillsboro",
    "state": "OR",
    "zip": "97123",
    "used": true,
    "addedAt": "2026-04-11T23:33:19.483Z"
  },
  {
    "id": 114,
    "address1": "3912 NE Brookwood Pkwy",
    "city": "Hillsboro",
    "state": "OR",
    "zip": "97124",
    "used": true,
    "addedAt": "2026-04-11T23:33:19.483Z"
  },
  {
    "id": 115,
    "address1": "1205 SE 10th Ave",
    "city": "Hillsboro",
    "state": "OR",
    "zip": "97123",
    "used": true,
    "addedAt": "2026-04-11T23:33:19.483Z"
  },
  {
    "id": 116,
    "address1": "2358 Pacific Ave",
    "city": "Forest Grove",
    "state": "OR",
    "zip": "97116",
    "used": true,
    "addedAt": "2026-04-11T23:33:19.483Z"
  },
  {
    "id": 117,
    "address1": "1740 Main St",
    "city": "Forest Grove",
    "state": "OR",
    "zip": "97116",
    "used": true,
    "addedAt": "2026-04-11T23:33:19.483Z"
  },
  {
    "id": 118,
    "address1": "3085 19th Ave",
    "city": "Forest Grove",
    "state": "OR",
    "zip": "97116",
    "used": true,
    "addedAt": "2026-04-11T23:33:19.483Z"
  },
  {
    "id": 119,
    "address1": "879 Elm St",
    "city": "Forest Grove",
    "state": "OR",
    "zip": "97116",
    "used": true,
    "addedAt": "2026-04-11T23:33:19.483Z"
  },
  {
    "id": 120,
    "address1": "4213 Gales Creek Rd",
    "city": "Forest Grove",
    "state": "OR",
    "zip": "97116",
    "used": true,
    "addedAt": "2026-04-11T23:33:19.483Z"
  },
  {
    "id": 121,
    "address1": "1534 NW Civic Dr",
    "city": "Gresham",
    "state": "OR",
    "zip": "97030",
    "used": true,
    "addedAt": "2026-04-11T23:33:19.483Z"
  },
  {
    "id": 122,
    "address1": "2871 SE Powell Valley Rd",
    "city": "Gresham",
    "state": "OR",
    "zip": "97080",
    "used": true,
    "addedAt": "2026-04-11T23:33:19.483Z"
  },
  {
    "id": 123,
    "address1": "4120 NE Division St",
    "city": "Gresham",
    "state": "OR",
    "zip": "97030",
    "used": true,
    "addedAt": "2026-04-11T23:33:19.483Z"
  },
  {
    "id": 124,
    "address1": "695 NW Eastman Pkwy",
    "city": "Gresham",
    "state": "OR",
    "zip": "97030",
    "used": true,
    "addedAt": "2026-04-11T23:33:19.483Z"
  },
  {
    "id": 125,
    "address1": "3247 SE Hogan Rd",
    "city": "Gresham",
    "state": "OR",
    "zip": "97080",
    "used": true,
    "addedAt": "2026-04-11T23:33:19.483Z"
  },
  {
    "id": 126,
    "address1": "1803 SW Pleasant View Dr",
    "city": "Gresham",
    "state": "OR",
    "zip": "97080",
    "used": true,
    "addedAt": "2026-04-11T23:33:19.483Z"
  },
  {
    "id": 127,
    "address1": "2410 NE Roberts Ave",
    "city": "Gresham",
    "state": "OR",
    "zip": "97030",
    "used": true,
    "addedAt": "2026-04-11T23:33:19.483Z"
  },
  {
    "id": 128,
    "address1": "5018 SE Stark St",
    "city": "Gresham",
    "state": "OR",
    "zip": "97030",
    "used": true,
    "addedAt": "2026-04-11T23:33:19.483Z"
  },
  {
    "id": 129,
    "address1": "937 NW Wallula Dr",
    "city": "Gresham",
    "state": "OR",
    "zip": "97030",
    "used": true,
    "addedAt": "2026-04-11T23:33:19.483Z"
  },
  {
    "id": 130,
    "address1": "3560 SE Orient Dr",
    "city": "Gresham",
    "state": "OR",
    "zip": "97080",
    "used": true,
    "addedAt": "2026-04-11T23:33:19.483Z"
  },
  {
    "id": 131,
    "address1": "1425 Boone Rd SE",
    "city": "Tigard",
    "state": "OR",
    "zip": "97224",
    "used": true,
    "addedAt": "2026-04-11T23:33:19.483Z"
  },
  {
    "id": 132,
    "address1": "2783 SW Pacific Hwy",
    "city": "Tigard",
    "state": "OR",
    "zip": "97223",
    "used": true,
    "addedAt": "2026-04-11T23:33:19.483Z"
  },
  {
    "id": 133,
    "address1": "4510 SW Hall Blvd",
    "city": "Tigard",
    "state": "OR",
    "zip": "97223",
    "used": true,
    "addedAt": "2026-04-11T23:33:19.483Z"
  },
  {
    "id": 134,
    "address1": "812 SW Hunziker St",
    "city": "Tigard",
    "state": "OR",
    "zip": "97223",
    "used": true,
    "addedAt": "2026-04-11T23:33:19.483Z"
  },
  {
    "id": 135,
    "address1": "3149 SW Durham Rd",
    "city": "Tigard",
    "state": "OR",
    "zip": "97224",
    "used": true,
    "addedAt": "2026-04-11T23:33:19.483Z"
  },
  {
    "id": 136,
    "address1": "1697 SW Gaarde St",
    "city": "Tigard",
    "state": "OR",
    "zip": "97224",
    "used": true,
    "addedAt": "2026-04-11T23:33:19.483Z"
  },
  {
    "id": 137,
    "address1": "2234 SW 72nd Ave",
    "city": "Tigard",
    "state": "OR",
    "zip": "97223",
    "used": true,
    "addedAt": "2026-04-11T23:33:19.483Z"
  },
  {
    "id": 138,
    "address1": "578 SW Burnham St",
    "city": "Tigard",
    "state": "OR",
    "zip": "97223",
    "used": true,
    "addedAt": "2026-04-11T23:33:19.483Z"
  },
  {
    "id": 139,
    "address1": "4012 SW Tigard St",
    "city": "Tigard",
    "state": "OR",
    "zip": "97223",
    "used": true,
    "addedAt": "2026-04-11T23:33:19.483Z"
  },
  {
    "id": 140,
    "address1": "1350 SW 121st Ave",
    "city": "Tigard",
    "state": "OR",
    "zip": "97223",
    "used": true,
    "addedAt": "2026-04-11T23:33:19.483Z"
  },
  {
    "id": 141,
    "address1": "2563 SW Boones Ferry Rd",
    "city": "Tualatin",
    "state": "OR",
    "zip": "97062",
    "used": true,
    "addedAt": "2026-04-11T23:33:19.483Z"
  },
  {
    "id": 142,
    "address1": "1891 SW Martinazzi Ave",
    "city": "Tualatin",
    "state": "OR",
    "zip": "97062",
    "used": true,
    "addedAt": "2026-04-11T23:33:19.483Z"
  },
  {
    "id": 143,
    "address1": "3720 SW Tualatin Sherwood Rd",
    "city": "Tualatin",
    "state": "OR",
    "zip": "97062",
    "used": true,
    "addedAt": "2026-04-11T23:33:19.483Z"
  },
  {
    "id": 144,
    "address1": "648 SW Sagert St",
    "city": "Tualatin",
    "state": "OR",
    "zip": "97062",
    "used": true,
    "addedAt": "2026-04-11T23:33:19.483Z"
  },
  {
    "id": 145,
    "address1": "4205 SW Nyberg St",
    "city": "Tualatin",
    "state": "OR",
    "zip": "97062",
    "used": true,
    "addedAt": "2026-04-11T23:33:19.483Z"
  },
  {
    "id": 146,
    "address1": "1532 SE Lava Dr",
    "city": "Milwaukie",
    "state": "OR",
    "zip": "97222",
    "used": true,
    "addedAt": "2026-04-11T23:33:19.483Z"
  },
  {
    "id": 147,
    "address1": "2847 SE Harrison St",
    "city": "Milwaukie",
    "state": "OR",
    "zip": "97222",
    "used": true,
    "addedAt": "2026-04-11T23:33:19.483Z"
  },
  {
    "id": 148,
    "address1": "4190 SE Lake Rd",
    "city": "Milwaukie",
    "state": "OR",
    "zip": "97267",
    "used": true,
    "addedAt": "2026-04-11T23:33:19.483Z"
  },
  {
    "id": 149,
    "address1": "729 SE Main St",
    "city": "Milwaukie",
    "state": "OR",
    "zip": "97222",
    "used": true,
    "addedAt": "2026-04-11T23:33:19.483Z"
  },
  {
    "id": 150,
    "address1": "3418 SE Monroe St",
    "city": "Milwaukie",
    "state": "OR",
    "zip": "97222",
    "used": true,
    "addedAt": "2026-04-11T23:33:19.483Z"
  },
  {
    "id": 151,
    "address1": "1245 SE Tacoma St",
    "city": "Milwaukie",
    "state": "OR",
    "zip": "97267",
    "used": true,
    "addedAt": "2026-04-11T23:33:19.483Z"
  },
  {
    "id": 152,
    "address1": "2601 SE Stanley Ave",
    "city": "Milwaukie",
    "state": "OR",
    "zip": "97267",
    "used": true,
    "addedAt": "2026-04-11T23:33:19.483Z"
  },
  {
    "id": 153,
    "address1": "530 SE River Rd",
    "city": "Milwaukie",
    "state": "OR",
    "zip": "97267",
    "used": true,
    "addedAt": "2026-04-11T23:33:19.483Z"
  },
  {
    "id": 154,
    "address1": "3875 SE Harmony Rd",
    "city": "Milwaukie",
    "state": "OR",
    "zip": "97222",
    "used": true,
    "addedAt": "2026-04-11T23:33:19.483Z"
  },
  {
    "id": 155,
    "address1": "1780 SE Oak Grove Blvd",
    "city": "Milwaukie",
    "state": "OR",
    "zip": "97267",
    "used": true,
    "addedAt": "2026-04-11T23:33:19.483Z"
  },
  {
    "id": 156,
    "address1": "2314 SW Sherwood Blvd",
    "city": "Sherwood",
    "state": "OR",
    "zip": "97140",
    "used": true,
    "addedAt": "2026-04-11T23:33:19.483Z"
  },
  {
    "id": 157,
    "address1": "1547 SW Meinecke Rd",
    "city": "Sherwood",
    "state": "OR",
    "zip": "97140",
    "used": true,
    "addedAt": "2026-04-11T23:33:19.483Z"
  },
  {
    "id": 158,
    "address1": "3890 SW Tualatin Sherwood Rd",
    "city": "Sherwood",
    "state": "OR",
    "zip": "97140",
    "used": true,
    "addedAt": "2026-04-11T23:33:19.483Z"
  },
  {
    "id": 159,
    "address1": "725 SW Railroad St",
    "city": "Sherwood",
    "state": "OR",
    "zip": "97140",
    "used": true,
    "addedAt": "2026-04-11T23:33:19.483Z"
  },
  {
    "id": 160,
    "address1": "4102 SW Langer Dr",
    "city": "Sherwood",
    "state": "OR",
    "zip": "97140",
    "used": true,
    "addedAt": "2026-04-11T23:33:19.483Z"
  },
  {
    "id": 161,
    "address1": "1832 Main St",
    "city": "Springfield",
    "state": "OR",
    "zip": "97477",
    "used": true,
    "addedAt": "2026-04-11T23:33:19.483Z"
  },
  {
    "id": 162,
    "address1": "2475 Mohawk Blvd",
    "city": "Springfield",
    "state": "OR",
    "zip": "97477",
    "used": true,
    "addedAt": "2026-04-11T23:33:19.483Z"
  },
  {
    "id": 163,
    "address1": "3140 Gateway St",
    "city": "Springfield",
    "state": "OR",
    "zip": "97477",
    "used": true,
    "addedAt": "2026-04-11T23:33:19.483Z"
  },
  {
    "id": 164,
    "address1": "689 S A St",
    "city": "Springfield",
    "state": "OR",
    "zip": "97477",
    "used": true,
    "addedAt": "2026-04-11T23:33:19.483Z"
  },
  {
    "id": 165,
    "address1": "4507 Main St",
    "city": "Springfield",
    "state": "OR",
    "zip": "97478",
    "used": true,
    "addedAt": "2026-04-11T23:33:19.483Z"
  },
  {
    "id": 166,
    "address1": "1293 Olympic St",
    "city": "Springfield",
    "state": "OR",
    "zip": "97477",
    "used": true,
    "addedAt": "2026-04-11T23:33:19.483Z"
  },
  {
    "id": 167,
    "address1": "2768 Centennial Blvd",
    "city": "Springfield",
    "state": "OR",
    "zip": "97477",
    "used": true,
    "addedAt": "2026-04-11T23:33:19.483Z"
  },
  {
    "id": 168,
    "address1": "530 Mill St",
    "city": "Springfield",
    "state": "OR",
    "zip": "97477",
    "used": true,
    "addedAt": "2026-04-11T23:33:19.483Z"
  },
  {
    "id": 169,
    "address1": "3421 Marcola Rd",
    "city": "Springfield",
    "state": "OR",
    "zip": "97477",
    "used": true,
    "addedAt": "2026-04-11T23:33:19.483Z"
  },
  {
    "id": 170,
    "address1": "1675 Harlow Rd",
    "city": "Springfield",
    "state": "OR",
    "zip": "97477",
    "used": true,
    "addedAt": "2026-04-11T23:33:19.483Z"
  },
  {
    "id": 171,
    "address1": "2147 W 6th St",
    "city": "The Dalles",
    "state": "OR",
    "zip": "97058",
    "used": true,
    "addedAt": "2026-04-11T23:33:19.483Z"
  },
  {
    "id": 172,
    "address1": "1389 E 12th St",
    "city": "The Dalles",
    "state": "OR",
    "zip": "97058",
    "used": true,
    "addedAt": "2026-04-11T23:33:19.483Z"
  },
  {
    "id": 173,
    "address1": "3540 Columbia View Dr",
    "city": "The Dalles",
    "state": "OR",
    "zip": "97058",
    "used": true,
    "addedAt": "2026-04-11T23:33:19.483Z"
  },
  {
    "id": 174,
    "address1": "872 Union St",
    "city": "The Dalles",
    "state": "OR",
    "zip": "97058",
    "used": true,
    "addedAt": "2026-04-11T23:33:19.483Z"
  },
  {
    "id": 175,
    "address1": "2618 Cherry Heights Rd",
    "city": "The Dalles",
    "state": "OR",
    "zip": "97058",
    "used": true,
    "addedAt": "2026-04-11T23:33:19.483Z"
  },
  {
    "id": 176,
    "address1": "1435 NE 3rd St",
    "city": "Pendleton",
    "state": "OR",
    "zip": "97801",
    "used": true,
    "addedAt": "2026-04-11T23:33:19.483Z"
  },
  {
    "id": 177,
    "address1": "2790 SW Dorion Ave",
    "city": "Pendleton",
    "state": "OR",
    "zip": "97801",
    "used": true,
    "addedAt": "2026-04-11T23:33:19.483Z"
  },
  {
    "id": 178,
    "address1": "547 SE Court Ave",
    "city": "Pendleton",
    "state": "OR",
    "zip": "97801",
    "used": true,
    "addedAt": "2026-04-11T23:33:19.483Z"
  },
  {
    "id": 179,
    "address1": "3218 SW Goodwin Pl",
    "city": "Pendleton",
    "state": "OR",
    "zip": "97801",
    "used": true,
    "addedAt": "2026-04-11T23:33:19.483Z"
  },
  {
    "id": 180,
    "address1": "1803 NW Carden Ave",
    "city": "Pendleton",
    "state": "OR",
    "zip": "97801",
    "used": true,
    "addedAt": "2026-04-11T23:33:19.483Z"
  },
  {
    "id": 181,
    "address1": "2540 6th St",
    "city": "Astoria",
    "state": "OR",
    "zip": "97103",
    "used": true,
    "addedAt": "2026-04-11T23:33:19.483Z"
  },
  {
    "id": 182,
    "address1": "1178 Commercial St",
    "city": "Astoria",
    "state": "OR",
    "zip": "97103",
    "used": true,
    "addedAt": "2026-04-11T23:33:19.483Z"
  },
  {
    "id": 183,
    "address1": "3825 Leif Erickson Dr",
    "city": "Astoria",
    "state": "OR",
    "zip": "97103",
    "used": true,
    "addedAt": "2026-04-11T23:33:19.483Z"
  },
  {
    "id": 184,
    "address1": "692 Marine Dr",
    "city": "Astoria",
    "state": "OR",
    "zip": "97103",
    "used": true,
    "addedAt": "2026-04-11T23:33:19.483Z"
  },
  {
    "id": 185,
    "address1": "4130 Franklin Ave",
    "city": "Astoria",
    "state": "OR",
    "zip": "97103",
    "used": true,
    "addedAt": "2026-04-11T23:33:19.483Z"
  },
  {
    "id": 186,
    "address1": "1547 NW Coast St",
    "city": "Newport",
    "state": "OR",
    "zip": "97365",
    "used": true,
    "addedAt": "2026-04-11T23:33:19.483Z"
  },
  {
    "id": 187,
    "address1": "2893 SW Elizabeth St",
    "city": "Newport",
    "state": "OR",
    "zip": "97365",
    "used": true,
    "addedAt": "2026-04-11T23:33:19.483Z"
  },
  {
    "id": 188,
    "address1": "435 NW Nye St",
    "city": "Newport",
    "state": "OR",
    "zip": "97365",
    "used": true,
    "addedAt": "2026-04-11T23:33:19.483Z"
  },
  {
    "id": 189,
    "address1": "3210 SE Ferry Slip Rd",
    "city": "Newport",
    "state": "OR",
    "zip": "97365",
    "used": true,
    "addedAt": "2026-04-11T23:33:19.483Z"
  },
  {
    "id": 190,
    "address1": "1780 N Coast Hwy",
    "city": "Newport",
    "state": "OR",
    "zip": "97365",
    "used": true,
    "addedAt": "2026-04-11T23:33:19.483Z"
  },
  {
    "id": 191,
    "address1": "2314 NW Oceanview Dr",
    "city": "Newport",
    "state": "OR",
    "zip": "97365",
    "used": true,
    "addedAt": "2026-04-11T23:33:19.483Z"
  },
  {
    "id": 192,
    "address1": "875 SW Alder St",
    "city": "Newport",
    "state": "OR",
    "zip": "97365",
    "used": true,
    "addedAt": "2026-04-11T23:33:19.483Z"
  },
  {
    "id": 193,
    "address1": "4018 SE Harborton Dr",
    "city": "Newport",
    "state": "OR",
    "zip": "97365",
    "used": true,
    "addedAt": "2026-04-11T23:33:19.483Z"
  },
  {
    "id": 194,
    "address1": "1523 NW Spring St",
    "city": "Newport",
    "state": "OR",
    "zip": "97365",
    "used": true,
    "addedAt": "2026-04-11T23:33:19.483Z"
  },
  {
    "id": 195,
    "address1": "3647 SW Abalone St",
    "city": "Newport",
    "state": "OR",
    "zip": "97365",
    "used": true,
    "addedAt": "2026-04-11T23:33:19.483Z"
  },
  {
    "id": 196,
    "address1": "1250 Broadway St",
    "city": "Seaside",
    "state": "OR",
    "zip": "97138",
    "used": true,
    "addedAt": "2026-04-11T23:33:19.483Z"
  },
  {
    "id": 197,
    "address1": "2478 N Promenade",
    "city": "Seaside",
    "state": "OR",
    "zip": "97138",
    "used": true,
    "addedAt": "2026-04-11T23:33:19.483Z"
  },
  {
    "id": 198,
    "address1": "3715 S Columbia St",
    "city": "Seaside",
    "state": "OR",
    "zip": "97138",
    "used": true,
    "addedAt": "2026-04-11T23:33:19.483Z"
  },
  {
    "id": 199,
    "address1": "890 Avenue U",
    "city": "Seaside",
    "state": "OR",
    "zip": "97138",
    "used": true,
    "addedAt": "2026-04-11T23:33:19.483Z"
  },
  {
    "id": 200,
    "address1": "1634 Holladay Dr",
    "city": "Seaside",
    "state": "OR",
    "zip": "97138",
    "used": true,
    "addedAt": "2026-04-11T23:33:19.483Z"
  },
  {
    "id": 201,
    "address1": "2345 NW Wall St",
    "city": "Bend",
    "state": "OR",
    "zip": "97703",
    "used": true,
    "addedAt": "2026-04-11T23:33:19.483Z"
  },
  {
    "id": 202,
    "address1": "4712 NW Crossing Dr",
    "city": "Bend",
    "state": "OR",
    "zip": "97703",
    "used": true,
    "addedAt": "2026-04-11T23:33:19.483Z"
  },
  {
    "id": 203,
    "address1": "1087 SW Simpson Ave",
    "city": "Bend",
    "state": "OR",
    "zip": "97702",
    "used": true,
    "addedAt": "2026-04-11T23:33:19.483Z"
  },
  {
    "id": 204,
    "address1": "3568 NE Purcell Blvd",
    "city": "Bend",
    "state": "OR",
    "zip": "97701",
    "used": true,
    "addedAt": "2026-04-11T23:33:19.483Z"
  },
  {
    "id": 205,
    "address1": "2190 SE Reed Market Rd",
    "city": "Bend",
    "state": "OR",
    "zip": "97702",
    "used": true,
    "addedAt": "2026-04-11T23:33:19.483Z"
  },
  {
    "id": 206,
    "address1": "5423 NW Pinery St",
    "city": "Bend",
    "state": "OR",
    "zip": "97703",
    "used": true,
    "addedAt": "2026-04-11T23:33:19.483Z"
  },
  {
    "id": 207,
    "address1": "1374 SW Knoll Ave",
    "city": "Bend",
    "state": "OR",
    "zip": "97702",
    "used": true,
    "addedAt": "2026-04-11T23:33:19.483Z"
  },
  {
    "id": 208,
    "address1": "2835 NE Conners Ave",
    "city": "Bend",
    "state": "OR",
    "zip": "97701",
    "used": true,
    "addedAt": "2026-04-11T23:33:19.483Z"
  },
  {
    "id": 209,
    "address1": "4021 SW Yew Ave",
    "city": "Redmond",
    "state": "OR",
    "zip": "97756",
    "used": true,
    "addedAt": "2026-04-11T23:33:19.483Z"
  },
  {
    "id": 210,
    "address1": "1568 NW Cedar Ave",
    "city": "Redmond",
    "state": "OR",
    "zip": "97756",
    "used": true,
    "addedAt": "2026-04-11T23:33:19.483Z"
  },
  {
    "id": 211,
    "address1": "3214 NW Hemlock Ave",
    "city": "McMinnville",
    "state": "OR",
    "zip": "97128",
    "used": true,
    "addedAt": "2026-04-11T23:33:19.483Z"
  },
  {
    "id": 212,
    "address1": "1780 SE Baker St",
    "city": "McMinnville",
    "state": "OR",
    "zip": "97128",
    "used": true,
    "addedAt": "2026-04-11T23:33:19.483Z"
  },
  {
    "id": 213,
    "address1": "2547 NE 3rd St",
    "city": "McMinnville",
    "state": "OR",
    "zip": "97128",
    "used": true,
    "addedAt": "2026-04-11T23:33:19.483Z"
  },
  {
    "id": 214,
    "address1": "895 SW Hill Rd",
    "city": "McMinnville",
    "state": "OR",
    "zip": "97128",
    "used": true,
    "addedAt": "2026-04-11T23:33:19.483Z"
  },
  {
    "id": 215,
    "address1": "4103 NW 2nd St",
    "city": "McMinnville",
    "state": "OR",
    "zip": "97128",
    "used": true,
    "addedAt": "2026-04-11T23:33:19.483Z"
  },
  {
    "id": 216,
    "address1": "1342 SE Adams St",
    "city": "McMinnville",
    "state": "OR",
    "zip": "97128",
    "used": true,
    "addedAt": "2026-04-11T23:33:19.483Z"
  },
  {
    "id": 217,
    "address1": "2879 NE Riverside Dr",
    "city": "McMinnville",
    "state": "OR",
    "zip": "97128",
    "used": true,
    "addedAt": "2026-04-11T23:33:19.483Z"
  },
  {
    "id": 218,
    "address1": "618 NW Alpine St",
    "city": "McMinnville",
    "state": "OR",
    "zip": "97128",
    "used": true,
    "addedAt": "2026-04-11T23:33:19.483Z"
  },
  {
    "id": 219,
    "address1": "3475 SE Stratus Ave",
    "city": "McMinnville",
    "state": "OR",
    "zip": "97128",
    "used": true,
    "addedAt": "2026-04-11T23:33:19.483Z"
  },
  {
    "id": 220,
    "address1": "1190 SW Booth Bend Rd",
    "city": "McMinnville",
    "state": "OR",
    "zip": "97128",
    "used": true,
    "addedAt": "2026-04-11T23:33:19.483Z"
  },
  {
    "id": 221,
    "address1": "2418 W Central Ave",
    "city": "Sutherlin",
    "state": "OR",
    "zip": "97479",
    "used": true,
    "addedAt": "2026-04-11T23:33:19.483Z"
  },
  {
    "id": 222,
    "address1": "1753 E Central Ave",
    "city": "Sutherlin",
    "state": "OR",
    "zip": "97479",
    "used": true,
    "addedAt": "2026-04-11T23:33:19.483Z"
  },
  {
    "id": 223,
    "address1": "3089 Nonpareil Rd",
    "city": "Sutherlin",
    "state": "OR",
    "zip": "97479",
    "used": true,
    "addedAt": "2026-04-11T23:33:19.483Z"
  },
  {
    "id": 224,
    "address1": "540 S Calapooia St",
    "city": "Sutherlin",
    "state": "OR",
    "zip": "97479",
    "used": true,
    "addedAt": "2026-04-11T23:33:19.483Z"
  },
  {
    "id": 225,
    "address1": "1920 Fort McKay Rd",
    "city": "Sutherlin",
    "state": "OR",
    "zip": "97479",
    "used": true,
    "addedAt": "2026-04-11T23:33:19.483Z"
  },
  {
    "id": 226,
    "address1": "3745 NE Greenwood Ave",
    "city": "Prineville",
    "state": "OR",
    "zip": "97754",
    "used": true,
    "addedAt": "2026-04-11T23:33:19.483Z"
  },
  {
    "id": 227,
    "address1": "1287 NW Lamonta Rd",
    "city": "Prineville",
    "state": "OR",
    "zip": "97754",
    "used": true,
    "addedAt": "2026-04-11T23:33:19.483Z"
  },
  {
    "id": 228,
    "address1": "2510 SE 3rd St",
    "city": "Prineville",
    "state": "OR",
    "zip": "97754",
    "used": true,
    "addedAt": "2026-04-11T23:33:19.483Z"
  },
  {
    "id": 229,
    "address1": "890 NW Madras Hwy",
    "city": "Prineville",
    "state": "OR",
    "zip": "97754",
    "used": true,
    "addedAt": "2026-04-11T23:33:19.483Z"
  },
  {
    "id": 230,
    "address1": "4123 NE Ochoco Hwy",
    "city": "Prineville",
    "state": "OR",
    "zip": "97754",
    "used": true,
    "addedAt": "2026-04-11T23:33:19.483Z"
  },
  {
    "id": 231,
    "address1": "1542 Washington Ave",
    "city": "La Grande",
    "state": "OR",
    "zip": "97850",
    "used": true,
    "addedAt": "2026-04-11T23:33:19.483Z"
  },
  {
    "id": 232,
    "address1": "2871 Adams Ave",
    "city": "La Grande",
    "state": "OR",
    "zip": "97850",
    "used": true,
    "addedAt": "2026-04-11T23:33:19.483Z"
  },
  {
    "id": 233,
    "address1": "3410 Cove Ave",
    "city": "La Grande",
    "state": "OR",
    "zip": "97850",
    "used": true,
    "addedAt": "2026-04-11T23:33:19.483Z"
  },
  {
    "id": 234,
    "address1": "785 Spruce St",
    "city": "La Grande",
    "state": "OR",
    "zip": "97850",
    "used": true,
    "addedAt": "2026-04-11T23:33:19.483Z"
  },
  {
    "id": 235,
    "address1": "2134 4th St",
    "city": "La Grande",
    "state": "OR",
    "zip": "97850",
    "used": true,
    "addedAt": "2026-04-11T23:33:19.483Z"
  },
  {
    "id": 236,
    "address1": "1823 SW Highland Ave",
    "city": "Klamath Falls",
    "state": "OR",
    "zip": "97601",
    "used": true,
    "addedAt": "2026-04-11T23:33:19.483Z"
  },
  {
    "id": 237,
    "address1": "3150 Washburn Way",
    "city": "Klamath Falls",
    "state": "OR",
    "zip": "97603",
    "used": true,
    "addedAt": "2026-04-11T23:33:19.483Z"
  },
  {
    "id": 238,
    "address1": "2475 Shasta Way",
    "city": "Klamath Falls",
    "state": "OR",
    "zip": "97601",
    "used": true,
    "addedAt": "2026-04-11T23:33:19.483Z"
  },
  {
    "id": 239,
    "address1": "910 Main St",
    "city": "Klamath Falls",
    "state": "OR",
    "zip": "97601",
    "used": true,
    "addedAt": "2026-04-11T23:33:19.483Z"
  },
  {
    "id": 240,
    "address1": "4287 S 6th St",
    "city": "Klamath Falls",
    "state": "OR",
    "zip": "97603",
    "used": true,
    "addedAt": "2026-04-11T23:33:19.483Z"
  },
  {
    "id": 241,
    "address1": "1638 Esplanade St",
    "city": "Klamath Falls",
    "state": "OR",
    "zip": "97601",
    "used": true,
    "addedAt": "2026-04-11T23:33:19.483Z"
  },
  {
    "id": 242,
    "address1": "2940 Altamont Dr",
    "city": "Klamath Falls",
    "state": "OR",
    "zip": "97603",
    "used": true,
    "addedAt": "2026-04-11T23:33:19.483Z"
  },
  {
    "id": 243,
    "address1": "735 Oak Ave",
    "city": "Klamath Falls",
    "state": "OR",
    "zip": "97601",
    "used": true,
    "addedAt": "2026-04-11T23:33:19.483Z"
  },
  {
    "id": 244,
    "address1": "3512 Homedale Rd",
    "city": "Klamath Falls",
    "state": "OR",
    "zip": "97603",
    "used": true,
    "addedAt": "2026-04-11T23:33:19.483Z"
  },
  {
    "id": 245,
    "address1": "1270 N Eldorado Ave",
    "city": "Klamath Falls",
    "state": "OR",
    "zip": "97601",
    "used": true,
    "addedAt": "2026-04-11T23:33:19.483Z"
  },
  {
    "id": 246,
    "address1": "2145 12th St",
    "city": "Hood River",
    "state": "OR",
    "zip": "97031",
    "used": true,
    "addedAt": "2026-04-11T23:33:19.483Z"
  },
  {
    "id": 247,
    "address1": "1578 Cascade Ave",
    "city": "Hood River",
    "state": "OR",
    "zip": "97031",
    "used": true,
    "addedAt": "2026-04-11T23:33:19.483Z"
  },
  {
    "id": 248,
    "address1": "3290 Belmont Dr",
    "city": "Hood River",
    "state": "OR",
    "zip": "97031",
    "used": true,
    "addedAt": "2026-04-11T23:33:19.483Z"
  },
  {
    "id": 249,
    "address1": "845 Oak St",
    "city": "Hood River",
    "state": "OR",
    "zip": "97031",
    "used": true,
    "addedAt": "2026-04-11T23:33:19.483Z"
  },
  {
    "id": 250,
    "address1": "4017 Barrett Dr",
    "city": "Hood River",
    "state": "OR",
    "zip": "97031",
    "used": true,
    "addedAt": "2026-04-11T23:33:19.483Z"
  },
  {
    "id": 251,
    "address1": "1935 Promontory Ave",
    "city": "Hood River",
    "state": "OR",
    "zip": "97031",
    "used": true,
    "addedAt": "2026-04-11T23:33:19.483Z"
  },
  {
    "id": 252,
    "address1": "2614 Wasco St",
    "city": "Hood River",
    "state": "OR",
    "zip": "97031",
    "used": true,
    "addedAt": "2026-04-11T23:33:19.483Z"
  },
  {
    "id": 253,
    "address1": "730 State St",
    "city": "Hood River",
    "state": "OR",
    "zip": "97031",
    "used": true,
    "addedAt": "2026-04-11T23:33:19.483Z"
  },
  {
    "id": 254,
    "address1": "3147 Country Club Rd",
    "city": "Hood River",
    "state": "OR",
    "zip": "97031",
    "used": true,
    "addedAt": "2026-04-11T23:33:19.483Z"
  },
  {
    "id": 255,
    "address1": "1480 Indian Creek Rd",
    "city": "Hood River",
    "state": "OR",
    "zip": "97031",
    "used": true,
    "addedAt": "2026-04-11T23:33:19.483Z"
  },
  {
    "id": 256,
    "address1": "2358 NW Arizona Ave",
    "city": "Hermiston",
    "state": "OR",
    "zip": "97838",
    "used": true,
    "addedAt": "2026-04-11T23:33:19.483Z"
  },
  {
    "id": 257,
    "address1": "1543 E Main St",
    "city": "Hermiston",
    "state": "OR",
    "zip": "97838",
    "used": true,
    "addedAt": "2026-04-11T23:33:19.483Z"
  },
  {
    "id": 258,
    "address1": "3712 SE 4th St",
    "city": "Hermiston",
    "state": "OR",
    "zip": "97838",
    "used": true,
    "addedAt": "2026-04-11T23:33:19.483Z"
  },
  {
    "id": 259,
    "address1": "890 NW 11th Pl",
    "city": "Hermiston",
    "state": "OR",
    "zip": "97838",
    "used": true,
    "addedAt": "2026-04-11T23:33:19.483Z"
  },
  {
    "id": 260,
    "address1": "4215 W Highland Ave",
    "city": "Hermiston",
    "state": "OR",
    "zip": "97838",
    "used": true,
    "addedAt": "2026-04-11T23:33:19.483Z"
  },
  {
    "id": 261,
    "address1": "1732 SE Court Ave",
    "city": "Hermiston",
    "state": "OR",
    "zip": "97838",
    "used": true,
    "addedAt": "2026-04-11T23:33:19.483Z"
  },
  {
    "id": 262,
    "address1": "2490 NE 10th St",
    "city": "Hermiston",
    "state": "OR",
    "zip": "97838",
    "used": true,
    "addedAt": "2026-04-11T23:33:19.483Z"
  },
  {
    "id": 263,
    "address1": "617 SW Elm Ave",
    "city": "Hermiston",
    "state": "OR",
    "zip": "97838",
    "used": true,
    "addedAt": "2026-04-11T23:33:19.483Z"
  },
  {
    "id": 264,
    "address1": "3085 NW Geer Rd",
    "city": "Hermiston",
    "state": "OR",
    "zip": "97838",
    "used": true,
    "addedAt": "2026-04-11T23:33:19.483Z"
  },
  {
    "id": 265,
    "address1": "1348 E Ridgeway Ave",
    "city": "Hermiston",
    "state": "OR",
    "zip": "97838",
    "used": true,
    "addedAt": "2026-04-11T23:33:19.483Z"
  },
  {
    "id": 266,
    "address1": "2541 SW 4th St",
    "city": "Ontario",
    "state": "OR",
    "zip": "97914",
    "used": true,
    "addedAt": "2026-04-11T23:33:19.483Z"
  },
  {
    "id": 267,
    "address1": "1873 NW 9th Ave",
    "city": "Ontario",
    "state": "OR",
    "zip": "97914",
    "used": true,
    "addedAt": "2026-04-11T23:33:19.483Z"
  },
  {
    "id": 268,
    "address1": "3420 E Idaho Ave",
    "city": "Ontario",
    "state": "OR",
    "zip": "97914",
    "used": true,
    "addedAt": "2026-04-11T23:33:19.483Z"
  },
  {
    "id": 269,
    "address1": "790 SW 1st St",
    "city": "Ontario",
    "state": "OR",
    "zip": "97914",
    "used": true,
    "addedAt": "2026-04-11T23:33:19.483Z"
  },
  {
    "id": 270,
    "address1": "4103 Alameda Dr",
    "city": "Ontario",
    "state": "OR",
    "zip": "97914",
    "used": true,
    "addedAt": "2026-04-11T23:33:19.483Z"
  },
  {
    "id": 271,
    "address1": "1625 SE 5th Ave",
    "city": "Canby",
    "state": "OR",
    "zip": "97013",
    "used": true,
    "addedAt": "2026-04-11T23:33:19.483Z"
  },
  {
    "id": 272,
    "address1": "2890 N Holly St",
    "city": "Canby",
    "state": "OR",
    "zip": "97013",
    "used": true,
    "addedAt": "2026-04-11T23:33:19.483Z"
  },
  {
    "id": 273,
    "address1": "3547 NW 3rd Ave",
    "city": "Canby",
    "state": "OR",
    "zip": "97013",
    "used": true,
    "addedAt": "2026-04-11T23:33:19.483Z"
  },
  {
    "id": 274,
    "address1": "812 S Ivy St",
    "city": "Canby",
    "state": "OR",
    "zip": "97013",
    "used": true,
    "addedAt": "2026-04-11T23:33:19.483Z"
  },
  {
    "id": 275,
    "address1": "4230 SE Township Rd",
    "city": "Canby",
    "state": "OR",
    "zip": "97013",
    "used": true,
    "addedAt": "2026-04-11T23:33:19.483Z"
  },
  {
    "id": 276,
    "address1": "1450 Pioneer Pkwy E",
    "city": "Springfield",
    "state": "OR",
    "zip": "97477",
    "used": true,
    "addedAt": "2026-04-11T23:33:19.483Z"
  },
  {
    "id": 277,
    "address1": "2713 Pheasant Blvd",
    "city": "Springfield",
    "state": "OR",
    "zip": "97477",
    "used": true,
    "addedAt": "2026-04-11T23:33:19.483Z"
  },
  {
    "id": 278,
    "address1": "3890 International Way",
    "city": "Springfield",
    "state": "OR",
    "zip": "97477",
    "used": true,
    "addedAt": "2026-04-11T23:33:19.483Z"
  },
  {
    "id": 279,
    "address1": "567 S 42nd St",
    "city": "Springfield",
    "state": "OR",
    "zip": "97478",
    "used": true,
    "addedAt": "2026-04-11T23:33:19.483Z"
  },
  {
    "id": 280,
    "address1": "2048 5th St",
    "city": "Springfield",
    "state": "OR",
    "zip": "97477",
    "used": true,
    "addedAt": "2026-04-11T23:33:19.483Z"
  },
  {
    "id": 281,
    "address1": "3215 NW Mt Washington Dr",
    "city": "Bend",
    "state": "OR",
    "zip": "97703",
    "used": true,
    "addedAt": "2026-04-11T23:33:19.483Z"
  },
  {
    "id": 282,
    "address1": "1847 SW Colorado Ave",
    "city": "Bend",
    "state": "OR",
    "zip": "97702",
    "used": true,
    "addedAt": "2026-04-11T23:33:19.483Z"
  },
  {
    "id": 283,
    "address1": "4530 NE Butler Market Rd",
    "city": "Bend",
    "state": "OR",
    "zip": "97701",
    "used": true,
    "addedAt": "2026-04-11T23:33:19.483Z"
  },
  {
    "id": 284,
    "address1": "2178 NW Clearwater Dr",
    "city": "Bend",
    "state": "OR",
    "zip": "97703",
    "used": true,
    "addedAt": "2026-04-11T23:33:19.483Z"
  },
  {
    "id": 285,
    "address1": "1023 SE Wilson Ave",
    "city": "Bend",
    "state": "OR",
    "zip": "97702",
    "used": true,
    "addedAt": "2026-04-11T23:33:19.483Z"
  },
  {
    "id": 286,
    "address1": "3540 River Rd N",
    "city": "Keizer",
    "state": "OR",
    "zip": "97303",
    "used": true,
    "addedAt": "2026-04-11T23:33:19.483Z"
  },
  {
    "id": 287,
    "address1": "1278 Chemawa Rd N",
    "city": "Keizer",
    "state": "OR",
    "zip": "97303",
    "used": true,
    "addedAt": "2026-04-11T23:33:19.483Z"
  },
  {
    "id": 288,
    "address1": "2891 Cherry Ave NE",
    "city": "Keizer",
    "state": "OR",
    "zip": "97303",
    "used": true,
    "addedAt": "2026-04-11T23:33:19.483Z"
  },
  {
    "id": 289,
    "address1": "745 Wheatland Rd N",
    "city": "Keizer",
    "state": "OR",
    "zip": "97303",
    "used": true,
    "addedAt": "2026-04-11T23:33:19.483Z"
  },
  {
    "id": 290,
    "address1": "4108 Verda Ln NE",
    "city": "Keizer",
    "state": "OR",
    "zip": "97303",
    "used": true,
    "addedAt": "2026-04-11T23:33:19.483Z"
  },
  {
    "id": 291,
    "address1": "1523 SW Willow Creek Dr",
    "city": "West Linn",
    "state": "OR",
    "zip": "97068",
    "used": true,
    "addedAt": "2026-04-11T23:33:19.483Z"
  },
  {
    "id": 292,
    "address1": "2847 Failing St",
    "city": "West Linn",
    "state": "OR",
    "zip": "97068",
    "used": true,
    "addedAt": "2026-04-11T23:33:19.483Z"
  },
  {
    "id": 293,
    "address1": "3410 Parker Rd",
    "city": "West Linn",
    "state": "OR",
    "zip": "97068",
    "used": true,
    "addedAt": "2026-04-11T23:33:19.483Z"
  },
  {
    "id": 294,
    "address1": "890 6th Ave",
    "city": "West Linn",
    "state": "OR",
    "zip": "97068",
    "used": true,
    "addedAt": "2026-04-11T23:33:19.483Z"
  },
  {
    "id": 295,
    "address1": "4235 Rosemont Rd",
    "city": "West Linn",
    "state": "OR",
    "zip": "97068",
    "used": true,
    "addedAt": "2026-04-11T23:33:19.483Z"
  },
  {
    "id": 296,
    "address1": "1670 Sunset Ave",
    "city": "West Linn",
    "state": "OR",
    "zip": "97068",
    "used": true,
    "addedAt": "2026-04-11T23:33:19.483Z"
  },
  {
    "id": 297,
    "address1": "2518 Bland Cir",
    "city": "West Linn",
    "state": "OR",
    "zip": "97068",
    "used": true,
    "addedAt": "2026-04-11T23:33:19.483Z"
  },
  {
    "id": 298,
    "address1": "738 Summit St",
    "city": "West Linn",
    "state": "OR",
    "zip": "97068",
    "used": true,
    "addedAt": "2026-04-11T23:33:19.483Z"
  },
  {
    "id": 299,
    "address1": "3145 Hidden Springs Rd",
    "city": "West Linn",
    "state": "OR",
    "zip": "97068",
    "used": true,
    "addedAt": "2026-04-11T23:33:19.483Z"
  },
  {
    "id": 300,
    "address1": "1892 Ostman Rd",
    "city": "West Linn",
    "state": "OR",
    "zip": "97068",
    "used": true,
    "addedAt": "2026-04-11T23:33:19.483Z"
  }
]